Metadata-Version: 1.2
Name: autonet
Version: 0.1.5
Summary: Some tools of network automated operation for multiple vendors
Home-page: https://github.com/zc8131868/Network-Operation
Author: Cheng Zheng
Author-email: zc8131868@gmail.com
License: MIT
Keywords: network,automated,operation
Platform: UNKNOWN
Classifier: Development Status :: 3 - Alpha
Classifier: Intended Audience :: Developers
Classifier: License :: OSI Approved :: MIT License
Classifier: Programming Language :: Python :: 3
Classifier: Programming Language :: Python :: 3.5
Classifier: Programming Language :: Python :: 3.6
Classifier: Programming Language :: Python :: 3.7
Requires-Python: >=3
